pbt/__init__.py
pbt/pbt_cli.py
pbt/process.py
pbt/prophecy_build_tool.py
pbt/utility.py
pbt/client/__init__.py
pbt/client/databricks.py
pbt/client/nexus.py
pbt/client/rest_client_factory.py
pbt/client/s3.py
pbt/client/airflow/__init__.py
pbt/client/airflow/airflow_utility.py
pbt/client/airflow/composer.py
pbt/client/airflow/mwaa.py
pbt/client/airflow/open_source.py
pbt/deployment/__init__.py
pbt/deployment/gems.py
pbt/deployment/pipeline.py
pbt/deployment/project.py
pbt/deployment/utils.py
pbt/deployment/jobs/__init__.py
pbt/deployment/jobs/airflow.py
pbt/deployment/jobs/databricks.py
pbt/deployment/jobs/utils.py
pbt/deployment/uploader/DatabricksPipelineUploader.py
pbt/deployment/uploader/DataprocPipelineUploader.py
pbt/deployment/uploader/EMRPipelineUploader.py
pbt/deployment/uploader/HdfsPipelineUploader.py
pbt/deployment/uploader/PipelineUploaderManager.py
pbt/deployment/uploader/__init__.py
pbt/entities/__init__.py
pbt/entities/project.py
pbt/utils/__init__.py
pbt/utils/constants.py
pbt/utils/exceptions.py
pbt/utils/pipeline_rename.py
pbt/utils/project_config.py
pbt/utils/project_models.py
pbt/utils/versioning.py
prophecy_build_tool-1.3.12.dist-info/licenses/LICENSE
prophecy_build_tool-1.3.12.dist-info/METADATA
prophecy_build_tool-1.3.12.dist-info/WHEEL
prophecy_build_tool-1.3.12.dist-info/entry_points.txt
prophecy_build_tool-1.3.12.dist-info/top_level.txt
prophecy_build_tool-1.3.12.dist-info/RECORD
