Metadata-Version: 2.4
Name: prophecy-build-tool
Version: 1.3.12
Summary: Prophecy-build-tool (PBT) provides utilities to build and distribute projects created from the Prophecy IDE.
Home-page: https://github.com/SimpleDataLabsInc/prophecy-build-tool
Author: Prophecy
Author-email: maciej@prophecy.io
Project-URL: Bug Tracker, https://github.com/SimpleDataLabsInc/prophecy-build-tool/issues
Classifier: Programming Language :: Python :: 3
Classifier: License :: OSI Approved :: MIT License
Classifier: Operating System :: OS Independent
Requires-Python: >=3.9,<3.13
License-File: LICENSE
Requires-Dist: requests>=2.28.0
Requires-Dist: PyYAML>=6.0
Requires-Dist: databricks-cli<=0.18.0,>=0.17.7
Requires-Dist: rich>=12.5.1
Requires-Dist: wheel~=0.41.3
Requires-Dist: build
Requires-Dist: google-cloud-secret-manager~=2.22.0
Requires-Dist: google-cloud-storage==2.10.0
Requires-Dist: pydantic~=1.10
Requires-Dist: pydantic-yaml==1.1.1
Requires-Dist: boto3~=1.34.120
Requires-Dist: tenacity==8.2.3
Requires-Dist: gitpython
Requires-Dist: semver
Requires-Dist: twine
Requires-Dist: jaraco.functools<=4.1.0
Requires-Dist: setuptools<81,>=75.3.2
Provides-Extra: test
Requires-Dist: pytest-html; extra == "test"
Requires-Dist: pytest-cov; extra == "test"
Requires-Dist: pytest; extra == "test"
Requires-Dist: pyspark<4.0.0,>=3.3.0; extra == "test"
Requires-Dist: mock; extra == "test"
Requires-Dist: parameterized; extra == "test"
Dynamic: author
Dynamic: author-email
Dynamic: classifier
Dynamic: description
Dynamic: description-content-type
Dynamic: home-page
Dynamic: license-file
Dynamic: project-url
Dynamic: provides-extra
Dynamic: requires-dist
Dynamic: requires-python
Dynamic: summary
